shipyard_hubspot/__init__.py
shipyard_hubspot/cli/__init__.py
shipyard_hubspot/cli/authtest.py
shipyard_hubspot/cli/csv_headers_assist.py
shipyard_hubspot/cli/export_list.py
shipyard_hubspot/cli/upload_data.py
shipyard_hubspot/hubspot.py
shipyard_hubspot/hubspot_utils.py
shipyard_hubspot-0.1.1.dist-info/METADATA
shipyard_hubspot-0.1.1.dist-info/WHEEL
shipyard_hubspot-0.1.1.dist-info/RECORD
