Metadata-Version: 2.1
Name: shipyard-hubspot
Version: 0.1.1
Summary: A local client for connecting and working with Hubspot APIs
Author: JR
Author-email: johnathan.rodriguez@shipyardapp.com
Requires-Python: >=3.9,<4.0
Classifier: Programming Language :: Python :: 3
Classifier: Programming Language :: Python :: 3.9
Classifier: Programming Language :: Python :: 3.10
Classifier: Programming Language :: Python :: 3.11
Requires-Dist: hubspot-api-client (>=8.1.0,<9.0.0)
Requires-Dist: requests (==2.31.0)
Requires-Dist: shipyard-templates (==0.3.1)
